[{"id":50,"time":1,"name":"Chacaya220->ElCobre220","bus_a":14,"bus_b":32,"flow":-33.3212855202,"value":-33.3212855202,"capacity":0.0},{"id":50,"time":2,"name":"Chacaya220->ElCobre220","bus_a":14,"bus_b":32,"flow":-33.7234455142,"value":-33.7234455142,"capacity":0.0},{"id":50,"time":3,"name":"Chacaya220->ElCobre220","bus_a":14,"bus_b":32,"flow":-33.7705623938,"value":-33.7705623938,"capacity":0.0},{"id":50,"time":4,"name":"Chacaya220->ElCobre220","bus_a":14,"bus_b":32,"flow":-41.9670969005,"value":-41.9670969005,"capacity":0.0},{"id":50,"time":5,"name":"Chacaya220->ElCobre220","bus_a":14,"bus_b":32,"flow":-41.1934638144,"value":-41.1934638144,"capacity":0.0},{"id":50,"time":6,"name":"Chacaya220->ElCobre220","bus_a":14,"bus_b":32,"flow":-41.6305649564,"value":-41.6305649564,"capacity":0.0},{"id":50,"time":7,"name":"Chacaya220->ElCobre220","bus_a":14,"bus_b":32,"flow":-38.3725902602,"value":-38.3725902602,"capacity":0.0},{"id":50,"time":8,"name":"Chacaya220->ElCobre220","bus_a":14,"bus_b":32,"flow":-36.4783687997,"value":-36.4783687997,"capacity":0.0},{"id":50,"time":9,"name":"Chacaya220->ElCobre220","bus_a":14,"bus_b":32,"flow":-25.388556052,"value":-25.388556052,"capacity":0.0},{"id":50,"time":10,"name":"Chacaya220->ElCobre220","bus_a":14,"bus_b":32,"flow":-7.4295304229,"value":-7.4295304229,"capacity":0.0},{"id":50,"time":11,"name":"Chacaya220->ElCobre220","bus_a":14,"bus_b":32,"flow":-1.7040443202,"value":-1.7040443202,"capacity":0.0},{"id":50,"time":12,"name":"Chacaya220->ElCobre220","bus_a":14,"bus_b":32,"flow":-2.7383854422,"value":-2.7383854422,"capacity":0.0},{"id":50,"time":13,"name":"Chacaya220->ElCobre220","bus_a":14,"bus_b":32,"flow":-0.4807497461,"value":-0.4807497461,"capacity":0.0},{"id":50,"time":14,"name":"Chacaya220->ElCobre220","bus_a":14,"bus_b":32,"flow":2.2241373808,"value":2.2241373808,"capacity":0.0},{"id":50,"time":15,"name":"Chacaya220->ElCobre220","bus_a":14,"bus_b":32,"flow":1.9021197008,"value":1.9021197008,"capacity":0.0},{"id":50,"time":16,"name":"Chacaya220->ElCobre220","bus_a":14,"bus_b":32,"flow":6.3086545206,"value":6.3086545206,"capacity":0.0},{"id":50,"time":17,"name":"Chacaya220->ElCobre220","bus_a":14,"bus_b":32,"flow":0.0027829017,"value":0.0027829017,"capacity":0.0},{"id":50,"time":18,"name":"Chacaya220->ElCobre220","bus_a":14,"bus_b":32,"flow":-19.1019929176,"value":-19.1019929176,"capacity":0.0},{"id":50,"time":19,"name":"Chacaya220->ElCobre220","bus_a":14,"bus_b":32,"flow":-23.1086831771,"value":-23.1086831771,"capacity":0.0},{"id":50,"time":20,"name":"Chacaya220->ElCobre220","bus_a":14,"bus_b":32,"flow":-29.4570217684,"value":-29.4570217684,"capacity":0.0},{"id":50,"time":21,"name":"Chacaya220->ElCobre220","bus_a":14,"bus_b":32,"flow":-28.9616817504,"value":-28.9616817504,"capacity":0.0},{"id":50,"time":22,"name":"Chacaya220->ElCobre220","bus_a":14,"bus_b":32,"flow":-32.2444561911,"value":-32.2444561911,"capacity":0.0},{"id":50,"time":23,"name":"Chacaya220->ElCobre220","bus_a":14,"bus_b":32,"flow":-31.5952357683,"value":-31.5952357683,"capacity":0.0},{"id":50,"time":24,"name":"Chacaya220->ElCobre220","bus_a":14,"bus_b":32,"flow":-30.9469039999,"value":-30.9469039999,"capacity":0.0},{"id":50,"time":25,"name":"Chacaya220->ElCobre220","bus_a":14,"bus_b":32,"flow":-29.7488147268,"value":-29.7488147268,"capacity":0.0},{"id":50,"time":26,"name":"Chacaya220->ElCobre220","bus_a":14,"bus_b":32,"flow":-29.2982973875,"value":-29.2982973875,"capacity":0.0},{"id":50,"time":27,"name":"Chacaya220->ElCobre220","bus_a":14,"bus_b":32,"flow":-32.0939894586,"value":-32.0939894586,"capacity":0.0},{"id":50,"time":28,"name":"Chacaya220->ElCobre220","bus_a":14,"bus_b":32,"flow":-29.4898612425,"value":-29.4898612425,"capacity":0.0},{"id":50,"time":29,"name":"Chacaya220->ElCobre220","bus_a":14,"bus_b":32,"flow":-29.4898612425,"value":-29.4898612425,"capacity":0.0},{"id":50,"time":30,"name":"Chacaya220->ElCobre220","bus_a":14,"bus_b":32,"flow":-29.4898612425,"value":-29.4898612425,"capacity":0.0},{"id":50,"time":31,"name":"Chacaya220->ElCobre220","bus_a":14,"bus_b":32,"flow":-23.8864615299,"value":-23.8864615299,"capacity":0.0},{"id":50,"time":32,"name":"Chacaya220->ElCobre220","bus_a":14,"bus_b":32,"flow":-24.8636545946,"value":-24.8636545946,"capacity":0.0},{"id":50,"time":33,"name":"Chacaya220->ElCobre220","bus_a":14,"bus_b":32,"flow":-26.5216962358,"value":-26.5216962358,"capacity":0.0},{"id":50,"time":34,"name":"Chacaya220->ElCobre220","bus_a":14,"bus_b":32,"flow":-10.6306518578,"value":-10.6306518578,"capacity":0.0},{"id":50,"time":35,"name":"Chacaya220->ElCobre220","bus_a":14,"bus_b":32,"flow":-7.0680036976,"value":-7.0680036976,"capacity":0.0},{"id":50,"time":36,"name":"Chacaya220->ElCobre220","bus_a":14,"bus_b":32,"flow":-1.7685739926,"value":-1.7685739926,"capacity":0.0},{"id":50,"time":37,"name":"Chacaya220->ElCobre220","bus_a":14,"bus_b":32,"flow":-1.7685739926,"value":-1.7685739926,"capacity":0.0},{"id":50,"time":38,"name":"Chacaya220->ElCobre220","bus_a":14,"bus_b":32,"flow":-1.7685739926,"value":-1.7685739926,"capacity":0.0},{"id":50,"time":39,"name":"Chacaya220->ElCobre220","bus_a":14,"bus_b":32,"flow":3.2394306828,"value":3.2394306828,"capacity":0.0},{"id":50,"time":40,"name":"Chacaya220->ElCobre220","bus_a":14,"bus_b":32,"flow":5.5113543908,"value":5.5113543908,"capacity":0.0},{"id":50,"time":41,"name":"Chacaya220->ElCobre220","bus_a":14,"bus_b":32,"flow":-0.1498404587,"value":-0.1498404587,"capacity":0.0},{"id":50,"time":42,"name":"Chacaya220->ElCobre220","bus_a":14,"bus_b":32,"flow":-15.2358950219,"value":-15.2358950219,"capacity":0.0},{"id":50,"time":43,"name":"Chacaya220->ElCobre220","bus_a":14,"bus_b":32,"flow":-11.7746896272,"value":-11.7746896272,"capacity":0.0},{"id":50,"time":44,"name":"Chacaya220->ElCobre220","bus_a":14,"bus_b":32,"flow":-17.1301463209,"value":-17.1301463209,"capacity":0.0},{"id":50,"time":45,"name":"Chacaya220->ElCobre220","bus_a":14,"bus_b":32,"flow":-18.801838638,"value":-18.801838638,"capacity":0.0},{"id":50,"time":46,"name":"Chacaya220->ElCobre220","bus_a":14,"bus_b":32,"flow":-20.01794125,"value":-20.01794125,"capacity":0.0},{"id":50,"time":47,"name":"Chacaya220->ElCobre220","bus_a":14,"bus_b":32,"flow":-19.6324917988,"value":-19.6324917988,"capacity":0.0},{"id":50,"time":48,"name":"Chacaya220->ElCobre220","bus_a":14,"bus_b":32,"flow":-22.0652722307,"value":-22.0652722307,"capacity":0.0},{"id":50,"time":49,"name":"Chacaya220->ElCobre220","bus_a":14,"bus_b":32,"flow":-25.8902530605,"value":-25.8902530605,"capacity":0.0},{"id":50,"time":50,"name":"Chacaya220->ElCobre220","bus_a":14,"bus_b":32,"flow":-25.4797890071,"value":-25.4797890071,"capacity":0.0},{"id":50,"time":51,"name":"Chacaya220->ElCobre220","bus_a":14,"bus_b":32,"flow":-30.7732095023,"value":-30.7732095023,"capacity":0.0},{"id":50,"time":52,"name":"Chacaya220->ElCobre220","bus_a":14,"bus_b":32,"flow":-29.8194131324,"value":-29.8194131324,"capacity":0.0},{"id":50,"time":53,"name":"Chacaya220->ElCobre220","bus_a":14,"bus_b":32,"flow":-29.8194131324,"value":-29.8194131324,"capacity":0.0},{"id":50,"time":54,"name":"Chacaya220->ElCobre220","bus_a":14,"bus_b":32,"flow":-30.3549175548,"value":-30.3549175548,"capacity":0.0},{"id":50,"time":55,"name":"Chacaya220->ElCobre220","bus_a":14,"bus_b":32,"flow":-24.4381311276,"value":-24.4381311276,"capacity":0.0},{"id":50,"time":56,"name":"Chacaya220->ElCobre220","bus_a":14,"bus_b":32,"flow":-26.2604694653,"value":-26.2604694653,"capacity":0.0},{"id":50,"time":57,"name":"Chacaya220->ElCobre220","bus_a":14,"bus_b":32,"flow":-25.8779995778,"value":-25.8779995778,"capacity":0.0},{"id":50,"time":58,"name":"Chacaya220->ElCobre220","bus_a":14,"bus_b":32,"flow":-8.8775519021,"value":-8.8775519021,"capacity":0.0},{"id":50,"time":59,"name":"Chacaya220->ElCobre220","bus_a":14,"bus_b":32,"flow":-4.5113890795,"value":-4.5113890795,"capacity":0.0},{"id":50,"time":60,"name":"Chacaya220->ElCobre220","bus_a":14,"bus_b":32,"flow":-4.5113890795,"value":-4.5113890795,"capacity":0.0},{"id":50,"time":61,"name":"Chacaya220->ElCobre220","bus_a":14,"bus_b":32,"flow":-4.5113890795,"value":-4.5113890795,"capacity":0.0},{"id":50,"time":62,"name":"Chacaya220->ElCobre220","bus_a":14,"bus_b":32,"flow":-4.5113890795,"value":-4.5113890795,"capacity":0.0},{"id":50,"time":63,"name":"Chacaya220->ElCobre220","bus_a":14,"bus_b":32,"flow":1.2303788338,"value":1.2303788338,"capacity":0.0},{"id":50,"time":64,"name":"Chacaya220->ElCobre220","bus_a":14,"bus_b":32,"flow":2.6244044141,"value":2.6244044141,"capacity":0.0},{"id":50,"time":65,"name":"Chacaya220->ElCobre220","bus_a":14,"bus_b":32,"flow":-1.908754273,"value":-1.908754273,"capacity":0.0},{"id":50,"time":66,"name":"Chacaya220->ElCobre220","bus_a":14,"bus_b":32,"flow":-21.9140978467,"value":-21.9140978467,"capacity":0.0},{"id":50,"time":67,"name":"Chacaya220->ElCobre220","bus_a":14,"bus_b":32,"flow":-16.7838513876,"value":-16.7838513876,"capacity":0.0},{"id":50,"time":68,"name":"Chacaya220->ElCobre220","bus_a":14,"bus_b":32,"flow":-21.9328615673,"value":-21.9328615673,"capacity":0.0},{"id":50,"time":69,"name":"Chacaya220->ElCobre220","bus_a":14,"bus_b":32,"flow":-21.3575352435,"value":-21.3575352435,"capacity":0.0},{"id":50,"time":70,"name":"Chacaya220->ElCobre220","bus_a":14,"bus_b":32,"flow":-22.7264395194,"value":-22.7264395194,"capacity":0.0},{"id":50,"time":71,"name":"Chacaya220->ElCobre220","bus_a":14,"bus_b":32,"flow":-22.2069276171,"value":-22.2069276171,"capacity":0.0},{"id":50,"time":72,"name":"Chacaya220->ElCobre220","bus_a":14,"bus_b":32,"flow":-22.889716044,"value":-22.889716044,"capacity":0.0},{"id":50,"time":73,"name":"Chacaya220->ElCobre220","bus_a":14,"bus_b":32,"flow":-24.0800918065,"value":-24.0800918065,"capacity":0.0},{"id":50,"time":74,"name":"Chacaya220->ElCobre220","bus_a":14,"bus_b":32,"flow":-24.69242025,"value":-24.69242025,"capacity":0.0},{"id":50,"time":75,"name":"Chacaya220->ElCobre220","bus_a":14,"bus_b":32,"flow":-32.0631818957,"value":-32.0631818957,"capacity":0.0},{"id":50,"time":76,"name":"Chacaya220->ElCobre220","bus_a":14,"bus_b":32,"flow":-26.94232538,"value":-26.94232538,"capacity":0.0},{"id":50,"time":77,"name":"Chacaya220->ElCobre220","bus_a":14,"bus_b":32,"flow":-26.94232538,"value":-26.94232538,"capacity":0.0},{"id":50,"time":78,"name":"Chacaya220->ElCobre220","bus_a":14,"bus_b":32,"flow":-26.94232538,"value":-26.94232538,"capacity":0.0},{"id":50,"time":79,"name":"Chacaya220->ElCobre220","bus_a":14,"bus_b":32,"flow":-26.94232538,"value":-26.94232538,"capacity":0.0},{"id":50,"time":80,"name":"Chacaya220->ElCobre220","bus_a":14,"bus_b":32,"flow":-41.570479634,"value":-41.570479634,"capacity":0.0},{"id":50,"time":81,"name":"Chacaya220->ElCobre220","bus_a":14,"bus_b":32,"flow":-32.6013412761,"value":-32.6013412761,"capacity":0.0},{"id":50,"time":82,"name":"Chacaya220->ElCobre220","bus_a":14,"bus_b":32,"flow":-13.2064284295,"value":-13.2064284295,"capacity":0.0},{"id":50,"time":83,"name":"Chacaya220->ElCobre220","bus_a":14,"bus_b":32,"flow":-11.3548897516,"value":-11.3548897516,"capacity":0.0},{"id":50,"time":84,"name":"Chacaya220->ElCobre220","bus_a":14,"bus_b":32,"flow":-11.3548897516,"value":-11.3548897516,"capacity":0.0},{"id":50,"time":85,"name":"Chacaya220->ElCobre220","bus_a":14,"bus_b":32,"flow":-7.9993929336,"value":-7.9993929336,"capacity":0.0},{"id":50,"time":86,"name":"Chacaya220->ElCobre220","bus_a":14,"bus_b":32,"flow":-7.9993929336,"value":-7.9993929336,"capacity":0.0},{"id":50,"time":87,"name":"Chacaya220->ElCobre220","bus_a":14,"bus_b":32,"flow":-7.9993929336,"value":-7.9993929336,"capacity":0.0},{"id":50,"time":88,"name":"Chacaya220->ElCobre220","bus_a":14,"bus_b":32,"flow":-7.9993929336,"value":-7.9993929336,"capacity":0.0},{"id":50,"time":89,"name":"Chacaya220->ElCobre220","bus_a":14,"bus_b":32,"flow":-20.1873103849,"value":-20.1873103849,"capacity":0.0},{"id":50,"time":90,"name":"Chacaya220->ElCobre220","bus_a":14,"bus_b":32,"flow":-20.1873103849,"value":-20.1873103849,"capacity":0.0},{"id":50,"time":91,"name":"Chacaya220->ElCobre220","bus_a":14,"bus_b":32,"flow":-23.8835027274,"value":-23.8835027274,"capacity":0.0},{"id":50,"time":92,"name":"Chacaya220->ElCobre220","bus_a":14,"bus_b":32,"flow":-31.2624132662,"value":-31.2624132662,"capacity":0.0},{"id":50,"time":93,"name":"Chacaya220->ElCobre220","bus_a":14,"bus_b":32,"flow":-24.2483029164,"value":-24.2483029164,"capacity":0.0},{"id":50,"time":94,"name":"Chacaya220->ElCobre220","bus_a":14,"bus_b":32,"flow":-24.2483029164,"value":-24.2483029164,"capacity":0.0},{"id":50,"time":95,"name":"Chacaya220->ElCobre220","bus_a":14,"bus_b":32,"flow":-24.2483029164,"value":-24.2483029164,"capacity":0.0},{"id":50,"time":96,"name":"Chacaya220->ElCobre220","bus_a":14,"bus_b":32,"flow":-26.8961683163,"value":-26.8961683163,"capacity":0.0},{"id":50,"time":97,"name":"Chacaya220->ElCobre220","bus_a":14,"bus_b":32,"flow":-27.6003096491,"value":-27.6003096491,"capacity":0.0},{"id":50,"time":98,"name":"Chacaya220->ElCobre220","bus_a":14,"bus_b":32,"flow":-31.7908327621,"value":-31.7908327621,"capacity":0.0},{"id":50,"time":99,"name":"Chacaya220->ElCobre220","bus_a":14,"bus_b":32,"flow":-26.0922405198,"value":-26.0922405198,"capacity":0.0},{"id":50,"time":100,"name":"Chacaya220->ElCobre220","bus_a":14,"bus_b":32,"flow":-26.0922405198,"value":-26.0922405198,"capacity":0.0},{"id":50,"time":101,"name":"Chacaya220->ElCobre220","bus_a":14,"bus_b":32,"flow":-38.2577541865,"value":-38.2577541865,"capacity":0.0},{"id":50,"time":102,"name":"Chacaya220->ElCobre220","bus_a":14,"bus_b":32,"flow":-38.2577541865,"value":-38.2577541865,"capacity":0.0},{"id":50,"time":103,"name":"Chacaya220->ElCobre220","bus_a":14,"bus_b":32,"flow":-38.2577541865,"value":-38.2577541865,"capacity":0.0},{"id":50,"time":104,"name":"Chacaya220->ElCobre220","bus_a":14,"bus_b":32,"flow":-38.2577541865,"value":-38.2577541865,"capacity":0.0},{"id":50,"time":105,"name":"Chacaya220->ElCobre220","bus_a":14,"bus_b":32,"flow":-38.2577541865,"value":-38.2577541865,"capacity":0.0},{"id":50,"time":106,"name":"Chacaya220->ElCobre220","bus_a":14,"bus_b":32,"flow":-17.1217102773,"value":-17.1217102773,"capacity":0.0},{"id":50,"time":107,"name":"Chacaya220->ElCobre220","bus_a":14,"bus_b":32,"flow":-12.8749480591,"value":-12.8749480591,"capacity":0.0},{"id":50,"time":108,"name":"Chacaya220->ElCobre220","bus_a":14,"bus_b":32,"flow":-12.8749480591,"value":-12.8749480591,"capacity":0.0},{"id":50,"time":109,"name":"Chacaya220->ElCobre220","bus_a":14,"bus_b":32,"flow":-12.4203742096,"value":-12.4203742096,"capacity":0.0},{"id":50,"time":110,"name":"Chacaya220->ElCobre220","bus_a":14,"bus_b":32,"flow":-12.4203742096,"value":-12.4203742096,"capacity":0.0},{"id":50,"time":111,"name":"Chacaya220->ElCobre220","bus_a":14,"bus_b":32,"flow":-12.4203742096,"value":-12.4203742096,"capacity":0.0},{"id":50,"time":112,"name":"Chacaya220->ElCobre220","bus_a":14,"bus_b":32,"flow":-12.4203742096,"value":-12.4203742096,"capacity":0.0},{"id":50,"time":113,"name":"Chacaya220->ElCobre220","bus_a":14,"bus_b":32,"flow":-12.4203742096,"value":-12.4203742096,"capacity":0.0},{"id":50,"time":114,"name":"Chacaya220->ElCobre220","bus_a":14,"bus_b":32,"flow":-12.4203742096,"value":-12.4203742096,"capacity":0.0},{"id":50,"time":115,"name":"Chacaya220->ElCobre220","bus_a":14,"bus_b":32,"flow":-22.6877271193,"value":-22.6877271193,"capacity":0.0},{"id":50,"time":116,"name":"Chacaya220->ElCobre220","bus_a":14,"bus_b":32,"flow":-30.611831583,"value":-30.611831583,"capacity":0.0},{"id":50,"time":117,"name":"Chacaya220->ElCobre220","bus_a":14,"bus_b":32,"flow":-31.092060762,"value":-31.092060762,"capacity":0.0},{"id":50,"time":118,"name":"Chacaya220->ElCobre220","bus_a":14,"bus_b":32,"flow":-28.3347480711,"value":-28.3347480711,"capacity":0.0},{"id":50,"time":119,"name":"Chacaya220->ElCobre220","bus_a":14,"bus_b":32,"flow":-28.3347480711,"value":-28.3347480711,"capacity":0.0},{"id":50,"time":120,"name":"Chacaya220->ElCobre220","bus_a":14,"bus_b":32,"flow":-29.4614006695,"value":-29.4614006695,"capacity":0.0},{"id":50,"time":121,"name":"Chacaya220->ElCobre220","bus_a":14,"bus_b":32,"flow":-27.0808189524,"value":-27.0808189524,"capacity":0.0},{"id":50,"time":122,"name":"Chacaya220->ElCobre220","bus_a":14,"bus_b":32,"flow":-29.6211530014,"value":-29.6211530014,"capacity":0.0},{"id":50,"time":123,"name":"Chacaya220->ElCobre220","bus_a":14,"bus_b":32,"flow":-25.3360438097,"value":-25.3360438097,"capacity":0.0},{"id":50,"time":124,"name":"Chacaya220->ElCobre220","bus_a":14,"bus_b":32,"flow":-24.7998772518,"value":-24.7998772518,"capacity":0.0},{"id":50,"time":125,"name":"Chacaya220->ElCobre220","bus_a":14,"bus_b":32,"flow":-24.7998772518,"value":-24.7998772518,"capacity":0.0},{"id":50,"time":126,"name":"Chacaya220->ElCobre220","bus_a":14,"bus_b":32,"flow":-24.7998772518,"value":-24.7998772518,"capacity":0.0},{"id":50,"time":127,"name":"Chacaya220->ElCobre220","bus_a":14,"bus_b":32,"flow":-28.3383752357,"value":-28.3383752357,"capacity":0.0},{"id":50,"time":128,"name":"Chacaya220->ElCobre220","bus_a":14,"bus_b":32,"flow":-28.5600175576,"value":-28.5600175576,"capacity":0.0},{"id":50,"time":129,"name":"Chacaya220->ElCobre220","bus_a":14,"bus_b":32,"flow":-31.4208959687,"value":-31.4208959687,"capacity":0.0},{"id":50,"time":130,"name":"Chacaya220->ElCobre220","bus_a":14,"bus_b":32,"flow":-12.954771772,"value":-12.954771772,"capacity":0.0},{"id":50,"time":131,"name":"Chacaya220->ElCobre220","bus_a":14,"bus_b":32,"flow":-5.2936075505,"value":-5.2936075505,"capacity":0.0},{"id":50,"time":132,"name":"Chacaya220->ElCobre220","bus_a":14,"bus_b":32,"flow":-5.2936075505,"value":-5.2936075505,"capacity":0.0},{"id":50,"time":133,"name":"Chacaya220->ElCobre220","bus_a":14,"bus_b":32,"flow":-5.2936075505,"value":-5.2936075505,"capacity":0.0},{"id":50,"time":134,"name":"Chacaya220->ElCobre220","bus_a":14,"bus_b":32,"flow":-5.2936075505,"value":-5.2936075505,"capacity":0.0},{"id":50,"time":135,"name":"Chacaya220->ElCobre220","bus_a":14,"bus_b":32,"flow":-5.2936075505,"value":-5.2936075505,"capacity":0.0},{"id":50,"time":136,"name":"Chacaya220->ElCobre220","bus_a":14,"bus_b":32,"flow":0.2872721712,"value":0.2872721712,"capacity":0.0},{"id":50,"time":137,"name":"Chacaya220->ElCobre220","bus_a":14,"bus_b":32,"flow":-17.3656016394,"value":-17.3656016394,"capacity":0.0},{"id":50,"time":138,"name":"Chacaya220->ElCobre220","bus_a":14,"bus_b":32,"flow":-17.3656016394,"value":-17.3656016394,"capacity":0.0},{"id":50,"time":139,"name":"Chacaya220->ElCobre220","bus_a":14,"bus_b":32,"flow":-20.4532972092,"value":-20.4532972092,"capacity":0.0},{"id":50,"time":140,"name":"Chacaya220->ElCobre220","bus_a":14,"bus_b":32,"flow":-25.3979738686,"value":-25.3979738686,"capacity":0.0},{"id":50,"time":141,"name":"Chacaya220->ElCobre220","bus_a":14,"bus_b":32,"flow":-25.2063114871,"value":-25.2063114871,"capacity":0.0},{"id":50,"time":142,"name":"Chacaya220->ElCobre220","bus_a":14,"bus_b":32,"flow":-25.2063114871,"value":-25.2063114871,"capacity":0.0},{"id":50,"time":143,"name":"Chacaya220->ElCobre220","bus_a":14,"bus_b":32,"flow":-25.2063114871,"value":-25.2063114871,"capacity":0.0},{"id":50,"time":144,"name":"Chacaya220->ElCobre220","bus_a":14,"bus_b":32,"flow":-23.5965070267,"value":-23.5965070267,"capacity":0.0},{"id":50,"time":145,"name":"Chacaya220->ElCobre220","bus_a":14,"bus_b":32,"flow":-26.3779529651,"value":-26.3779529651,"capacity":0.0},{"id":50,"time":146,"name":"Chacaya220->ElCobre220","bus_a":14,"bus_b":32,"flow":-33.7847335807,"value":-33.7847335807,"capacity":0.0},{"id":50,"time":147,"name":"Chacaya220->ElCobre220","bus_a":14,"bus_b":32,"flow":-25.3400825989,"value":-25.3400825989,"capacity":0.0},{"id":50,"time":148,"name":"Chacaya220->ElCobre220","bus_a":14,"bus_b":32,"flow":-25.3400825989,"value":-25.3400825989,"capacity":0.0},{"id":50,"time":149,"name":"Chacaya220->ElCobre220","bus_a":14,"bus_b":32,"flow":-25.3400825989,"value":-25.3400825989,"capacity":0.0},{"id":50,"time":150,"name":"Chacaya220->ElCobre220","bus_a":14,"bus_b":32,"flow":-25.3400825989,"value":-25.3400825989,"capacity":0.0},{"id":50,"time":151,"name":"Chacaya220->ElCobre220","bus_a":14,"bus_b":32,"flow":-26.8524323207,"value":-26.8524323207,"capacity":0.0},{"id":50,"time":152,"name":"Chacaya220->ElCobre220","bus_a":14,"bus_b":32,"flow":-27.8257180439,"value":-27.8257180439,"capacity":0.0},{"id":50,"time":153,"name":"Chacaya220->ElCobre220","bus_a":14,"bus_b":32,"flow":-31.0284872339,"value":-31.0284872339,"capacity":0.0},{"id":50,"time":154,"name":"Chacaya220->ElCobre220","bus_a":14,"bus_b":32,"flow":-11.6082278679,"value":-11.6082278679,"capacity":0.0},{"id":50,"time":155,"name":"Chacaya220->ElCobre220","bus_a":14,"bus_b":32,"flow":-11.6082278679,"value":-11.6082278679,"capacity":0.0},{"id":50,"time":156,"name":"Chacaya220->ElCobre220","bus_a":14,"bus_b":32,"flow":-11.6082278679,"value":-11.6082278679,"capacity":0.0},{"id":50,"time":157,"name":"Chacaya220->ElCobre220","bus_a":14,"bus_b":32,"flow":-7.3452052669,"value":-7.3452052669,"capacity":0.0},{"id":50,"time":158,"name":"Chacaya220->ElCobre220","bus_a":14,"bus_b":32,"flow":-4.5764597487,"value":-4.5764597487,"capacity":0.0},{"id":50,"time":159,"name":"Chacaya220->ElCobre220","bus_a":14,"bus_b":32,"flow":-4.5764597487,"value":-4.5764597487,"capacity":0.0},{"id":50,"time":160,"name":"Chacaya220->ElCobre220","bus_a":14,"bus_b":32,"flow":-4.5764597487,"value":-4.5764597487,"capacity":0.0},{"id":50,"time":161,"name":"Chacaya220->ElCobre220","bus_a":14,"bus_b":32,"flow":-28.5011599713,"value":-28.5011599713,"capacity":0.0},{"id":50,"time":162,"name":"Chacaya220->ElCobre220","bus_a":14,"bus_b":32,"flow":-28.5011599713,"value":-28.5011599713,"capacity":0.0},{"id":50,"time":163,"name":"Chacaya220->ElCobre220","bus_a":14,"bus_b":32,"flow":-28.5011599713,"value":-28.5011599713,"capacity":0.0},{"id":50,"time":164,"name":"Chacaya220->ElCobre220","bus_a":14,"bus_b":32,"flow":-26.8212446806,"value":-26.8212446806,"capacity":0.0},{"id":50,"time":165,"name":"Chacaya220->ElCobre220","bus_a":14,"bus_b":32,"flow":-24.4600866276,"value":-24.4600866276,"capacity":0.0},{"id":50,"time":166,"name":"Chacaya220->ElCobre220","bus_a":14,"bus_b":32,"flow":-24.4600866276,"value":-24.4600866276,"capacity":0.0},{"id":50,"time":167,"name":"Chacaya220->ElCobre220","bus_a":14,"bus_b":32,"flow":-24.4600866276,"value":-24.4600866276,"capacity":0.0},{"id":50,"time":168,"name":"Chacaya220->ElCobre220","bus_a":14,"bus_b":32,"flow":-25.4867307923,"value":-25.4867307923,"capacity":0.0}]